system_hotkey/__init__.py
system_hotkey/keysymdef.py
system_hotkey/system_hotkey.py
system_hotkey/util.py
system_hotkey/xpybutil_keybind.py
system_hotkey310-1.0.5.dist-info/AUTHORS.rst
system_hotkey310-1.0.5.dist-info/LICENSE
system_hotkey310-1.0.5.dist-info/METADATA
system_hotkey310-1.0.5.dist-info/WHEEL
system_hotkey310-1.0.5.dist-info/top_level.txt
system_hotkey310-1.0.5.dist-info/RECORD
