Metadata-Version: 2.1
Name: system-hotkey310
Version: 1.0.5
Summary: System wide hotkeys
Home-page: https://github.com/hhannine/system_hotkey310
Author: Henri Hänninen
Author-email: henri.j.hanninen@gmail.com
License: BSD3
Keywords: hotkeys python3 shortcutkeys shortuct x11 windows
Classifier: Development Status :: 4 - Beta
Classifier: Intended Audience :: Developers
Classifier: Operating System :: OS Independent
Classifier: License :: OSI Approved :: BSD License
Classifier: Programming Language :: Python :: 3
License-File: LICENSE
License-File: AUTHORS.rst
